{
  "schema_version": "intel_source_registry_raw_intel_v2",
  "created_date_kst": "2026-05-07",
  "purpose": "RSS-first intel-crawl seed for the existing market-ingest major-50 receive universe.",
  "universe_source_path": "external://market-ingest/major-50",
  "selection_rules": {
    "do_not_recompute_trade_universe": true,
    "include_fetch_methods": ["rss", "rest_api", "html_crawl"],
    "exclude_fetch_methods": ["webhook", "file_drop", "manual_feed"],
    "exclude_if": [
      "requires login",
      "requires private API",
      "returns HTML for expected feed",
      "returns WAF or bot challenge",
      "needs headless browser",
      "community firehose without source budget"
    ],
    "use": "context and research evidence only; not a standalone trading signal"
  },
  "coverage": {
    "universe_asset_count": 50,
    "enabled_source_count": 42,
    "available_disabled_source_count": 16,
    "global_rss_source_count": 13,
    "asset_specific_rss_source_count": 28,
    "exchange_notice_rest_source_count": 3,
    "funding_rest_source_count": 3,
    "social_reaction_rss_enabled_count": 0,
    "social_reaction_rss_available_disabled_count": 12,
    "governance_rss_source_count": 3,
    "developer_activity_atom_source_count": 16,
    "asset_specific_coverage_count": 16,
    "asset_specific_covered_assets": [
      "AAVE",
      "ADA",
      "AVAX",
      "BCH",
      "BTC",
      "DOGE",
      "ETH",
      "LINK",
      "LTC",
      "NEAR",
      "SOL",
      "SUI",
      "TON",
      "TRX",
      "UNI",
      "ZEC"
    ]
  },
  "universe_assets": [
    { "asset": "USDC", "reference_symbol_native": "USDCUSDT", "rss_seed_status": "global_news_only" },
    { "asset": "BTC", "reference_symbol_native": "BTCUSDT", "rss_seed_status": "asset_specific_verified" },
    { "asset": "ETH", "reference_symbol_native": "ETHUSDT", "rss_seed_status": "asset_specific_verified" },
    { "asset": "SOL", "reference_symbol_native": "SOLUSDT", "rss_seed_status": "asset_specific_verified" },
    { "asset": "TON", "reference_symbol_native": "TONUSDT", "rss_seed_status": "asset_specific_verified" },
    { "asset": "ZEC", "reference_symbol_native": "ZECUSDT", "rss_seed_status": "asset_specific_verified" },
    { "asset": "BNB", "reference_symbol_native": "BNBUSDT", "rss_seed_status": "global_news_only" },
    { "asset": "XRP", "reference_symbol_native": "XRPUSDT", "rss_seed_status": "global_news_only" },
    { "asset": "DOGE", "reference_symbol_native": "DOGEUSDT", "rss_seed_status": "asset_specific_verified" },
    { "asset": "TST", "reference_symbol_native": "TSTUSDT", "rss_seed_status": "global_news_only" },
    { "asset": "USD1", "reference_symbol_native": "USD1USDT", "rss_seed_status": "global_news_only" },
    { "asset": "DOGS", "reference_symbol_native": "DOGSUSDT", "rss_seed_status": "global_news_only" },
    { "asset": "CHIP", "reference_symbol_native": "CHIPUSDT", "rss_seed_status": "global_news_only" },
    { "asset": "DASH", "reference_symbol_native": "DASHUSDT", "rss_seed_status": "global_news_only" },
    { "asset": "LUNC", "reference_symbol_native": "LUNCUSDT", "rss_seed_status": "global_news_only" },
    { "asset": "PEPE", "reference_symbol_native": "PEPEUSDT", "rss_seed_status": "global_news_only" },
    { "asset": "LINK", "reference_symbol_native": "LINKUSDT", "rss_seed_status": "asset_specific_verified" },
    { "asset": "PENGU", "reference_symbol_native": "PENGUUSDT", "rss_seed_status": "global_news_only" },
    { "asset": "TRX", "reference_symbol_native": "TRXUSDT", "rss_seed_status": "asset_specific_verified" },
    { "asset": "FDUSD", "reference_symbol_native": "FDUSDUSDT", "rss_seed_status": "global_news_only" },
    { "asset": "ADA", "reference_symbol_native": "ADAUSDT", "rss_seed_status": "asset_specific_verified" },
    { "asset": "ENA", "reference_symbol_native": "ENAUSDT", "rss_seed_status": "global_news_only" },
    { "asset": "GIGGLE", "reference_symbol_native": "GIGGLEUSDT", "rss_seed_status": "global_news_only" },
    { "asset": "TAO", "reference_symbol_native": "TAOUSDT", "rss_seed_status": "global_news_only" },
    { "asset": "ONDO", "reference_symbol_native": "ONDOUSDT", "rss_seed_status": "global_news_only" },
    { "asset": "PAXG", "reference_symbol_native": "PAXGUSDT", "rss_seed_status": "global_news_only" },
    { "asset": "PENDLE", "reference_symbol_native": "PENDLEUSDT", "rss_seed_status": "global_news_only" },
    { "asset": "SUI", "reference_symbol_native": "SUIUSDT", "rss_seed_status": "asset_specific_verified" },
    { "asset": "LTC", "reference_symbol_native": "LTCUSDT", "rss_seed_status": "asset_specific_verified" },
    { "asset": "XAUT", "reference_symbol_native": "XAUTUSDT", "rss_seed_status": "global_news_only" },
    { "asset": "WLFI", "reference_symbol_native": "WLFIUSDT", "rss_seed_status": "global_news_only" },
    { "asset": "EUR", "reference_symbol_native": "EURUSDT", "rss_seed_status": "global_news_only" },
    { "asset": "AVAX", "reference_symbol_native": "AVAXUSDT", "rss_seed_status": "asset_specific_verified" },
    { "asset": "BIO", "reference_symbol_native": "BIOUSDT", "rss_seed_status": "global_news_only" },
    { "asset": "NEAR", "reference_symbol_native": "NEARUSDT", "rss_seed_status": "asset_specific_verified" },
    { "asset": "TRUMP", "reference_symbol_native": "TRUMPUSDT", "rss_seed_status": "global_news_only" },
    { "asset": "BCH", "reference_symbol_native": "BCHUSDT", "rss_seed_status": "asset_specific_verified" },
    { "asset": "RLUSD", "reference_symbol_native": "RLUSDUSDT", "rss_seed_status": "global_news_only" },
    { "asset": "HIVE", "reference_symbol_native": "HIVEUSDT", "rss_seed_status": "global_news_only" },
    { "asset": "MEGA", "reference_symbol_native": "MEGAUSDT", "rss_seed_status": "global_news_only" },
    { "asset": "NOT", "reference_symbol_native": "NOTUSDT", "rss_seed_status": "global_news_only" },
    { "asset": "NEIRO", "reference_symbol_native": "NEIROUSDT", "rss_seed_status": "global_news_only" },
    { "asset": "ZBT", "reference_symbol_native": "ZBTUSDT", "rss_seed_status": "global_news_only" },
    { "asset": "UNI", "reference_symbol_native": "UNIUSDT", "rss_seed_status": "asset_specific_verified" },
    { "asset": "ZAMA", "reference_symbol_native": "ZAMAUSDT", "rss_seed_status": "global_news_only" },
    { "asset": "XUSD", "reference_symbol_native": "XUSDUSDT", "rss_seed_status": "global_news_only" },
    { "asset": "HMSTR", "reference_symbol_native": "HMSTRUSDT", "rss_seed_status": "global_news_only" },
    { "asset": "AAVE", "reference_symbol_native": "AAVEUSDT", "rss_seed_status": "asset_specific_verified" },
    { "asset": "ORDI", "reference_symbol_native": "ORDIUSDT", "rss_seed_status": "global_news_only" },
    { "asset": "U", "reference_symbol_native": "UUSDT", "rss_seed_status": "global_news_only" }
  ],
  "sources": [
    {
      "source_id": "news_coindesk_rss",
      "source_category": "news",
      "source_name": "CoinDesk RSS",
      "source_url": "https://www.coindesk.com/arc/outboundfeeds/rss",
      "fetch_method": "rss",
      "trust_tier": "T1",
      "cadence_tier": "medium",
      "language_hint": "en",
      "enabled": true,
      "top50_relevance_mode": "symbol_alias_match",
      "applies_to_assets": "all_major_50"
    },
    {
      "source_id": "news_cointelegraph_rss",
      "source_category": "news",
      "source_name": "Cointelegraph RSS",
      "source_url": "https://cointelegraph.com/rss",
      "fetch_method": "rss",
      "trust_tier": "T1",
      "cadence_tier": "medium",
      "language_hint": "en",
      "enabled": true,
      "top50_relevance_mode": "symbol_alias_match",
      "applies_to_assets": "all_major_50"
    },
    {
      "source_id": "news_decrypt_rss",
      "source_category": "news",
      "source_name": "Decrypt RSS",
      "source_url": "https://decrypt.co/feed",
      "fetch_method": "rss",
      "trust_tier": "T1",
      "cadence_tier": "medium",
      "language_hint": "en",
      "enabled": true,
      "top50_relevance_mode": "symbol_alias_match",
      "applies_to_assets": "all_major_50"
    },
    {
      "source_id": "news_theblock_rss",
      "source_category": "news",
      "source_name": "The Block RSS",
      "source_url": "https://www.theblock.co/rss.xml",
      "fetch_method": "rss",
      "trust_tier": "T1",
      "cadence_tier": "medium",
      "language_hint": "en",
      "enabled": true,
      "top50_relevance_mode": "symbol_alias_match",
      "applies_to_assets": "all_major_50"
    },
    {
      "source_id": "news_cryptoslate_rss",
      "source_category": "news",
      "source_name": "CryptoSlate RSS",
      "source_url": "https://cryptoslate.com/feed/",
      "fetch_method": "rss",
      "trust_tier": "T1",
      "cadence_tier": "medium",
      "language_hint": "en",
      "enabled": true,
      "top50_relevance_mode": "symbol_alias_match",
      "applies_to_assets": "all_major_50"
    },
    {
      "source_id": "news_beincrypto_rss",
      "source_category": "news",
      "source_name": "BeInCrypto RSS",
      "source_url": "https://beincrypto.com/feed/",
      "fetch_method": "rss",
      "trust_tier": "T1",
      "cadence_tier": "medium",
      "language_hint": "en",
      "enabled": true,
      "top50_relevance_mode": "symbol_alias_match",
      "applies_to_assets": "all_major_50"
    },
    {
      "source_id": "news_cryptopotato_rss",
      "source_category": "news",
      "source_name": "CryptoPotato RSS",
      "source_url": "https://cryptopotato.com/feed/",
      "fetch_method": "rss",
      "trust_tier": "T1",
      "cadence_tier": "medium",
      "language_hint": "en",
      "enabled": true,
      "top50_relevance_mode": "symbol_alias_match",
      "applies_to_assets": "all_major_50"
    },
    {
      "source_id": "news_bitcoinmagazine_rss",
      "source_category": "news",
      "source_name": "Bitcoin Magazine RSS",
      "source_url": "https://bitcoinmagazine.com/.rss/full/",
      "fetch_method": "rss",
      "trust_tier": "T1",
      "cadence_tier": "medium",
      "language_hint": "en",
      "enabled": true,
      "top50_relevance_mode": "symbol_alias_match",
      "applies_to_assets": "all_major_50"
    },
    {
      "source_id": "news_blockworks_rss",
      "source_category": "news",
      "source_name": "Blockworks RSS",
      "source_url": "https://blockworks.co/feed",
      "fetch_method": "rss",
      "trust_tier": "T1",
      "cadence_tier": "medium",
      "language_hint": "en",
      "enabled": true,
      "top50_relevance_mode": "symbol_alias_match",
      "applies_to_assets": "all_major_50"
    },
    {
      "source_id": "news_ambcrypto_rss",
      "source_category": "news",
      "source_name": "AMBCrypto RSS",
      "source_url": "https://ambcrypto.com/feed/",
      "fetch_method": "rss",
      "trust_tier": "T1",
      "cadence_tier": "medium",
      "language_hint": "en",
      "enabled": true,
      "top50_relevance_mode": "symbol_alias_match",
      "applies_to_assets": "all_major_50"
    },
    {
      "source_id": "news_newsbtc_rss",
      "source_category": "news",
      "source_name": "NewsBTC RSS",
      "source_url": "https://www.newsbtc.com/feed/",
      "fetch_method": "rss",
      "trust_tier": "T1",
      "cadence_tier": "medium",
      "language_hint": "en",
      "enabled": true,
      "top50_relevance_mode": "symbol_alias_match",
      "applies_to_assets": "all_major_50"
    },
    {
      "source_id": "news_coingape_rss",
      "source_category": "news",
      "source_name": "CoinGape RSS",
      "source_url": "https://coingape.com/feed/",
      "fetch_method": "rss",
      "trust_tier": "T1",
      "cadence_tier": "medium",
      "language_hint": "en",
      "enabled": true,
      "top50_relevance_mode": "symbol_alias_match",
      "applies_to_assets": "all_major_50"
    },
    {
      "source_id": "exchange_binance_listing_rest",
      "source_category": "exchange_notice",
      "source_name": "Binance New Cryptocurrency Listing Announcements",
      "source_url": "https://www.binance.com/bapi/composite/v1/public/cms/article/list/query?type=1&pageNo=1&pageSize=10&catalogId=48",
      "fetch_method": "rest_api",
      "adapter": "binance_cms_announcement_list",
      "max_items_per_run": 10,
      "trust_tier": "T0",
      "cadence_tier": "high",
      "language_hint": "en",
      "enabled": true,
      "top50_relevance_mode": "symbol_alias_match",
      "applies_to_assets": "all_major_50"
    },
    {
      "source_id": "exchange_binance_delisting_rest",
      "source_category": "exchange_notice",
      "source_name": "Binance Delisting Announcements",
      "source_url": "https://www.binance.com/bapi/composite/v1/public/cms/article/list/query?type=1&pageNo=1&pageSize=10&catalogId=161",
      "fetch_method": "rest_api",
      "adapter": "binance_cms_announcement_list",
      "max_items_per_run": 10,
      "trust_tier": "T0",
      "cadence_tier": "high",
      "language_hint": "en",
      "enabled": true,
      "top50_relevance_mode": "symbol_alias_match",
      "applies_to_assets": "all_major_50"
    },
    {
      "source_id": "exchange_binance_maintenance_rest",
      "source_category": "exchange_notice",
      "source_name": "Binance Maintenance Announcements",
      "source_url": "https://www.binance.com/bapi/composite/v1/public/cms/article/list/query?type=1&pageNo=1&pageSize=10&catalogId=157",
      "fetch_method": "rest_api",
      "adapter": "binance_cms_announcement_list",
      "max_items_per_run": 10,
      "trust_tier": "T0",
      "cadence_tier": "high",
      "language_hint": "en",
      "enabled": true,
      "top50_relevance_mode": "symbol_alias_match",
      "applies_to_assets": "all_major_50"
    },
    {
      "source_id": "derivatives_binance_usdm_funding_rate_rest",
      "source_category": "funding",
      "source_name": "Binance USD-M Futures Latest Funding Rate",
      "source_url": "https://fapi.binance.com/fapi/v1/fundingRate",
      "fetch_method": "rest_api",
      "adapter": "binance_usdm_funding_rate_latest",
      "max_items_per_run": 50,
      "trust_tier": "T1",
      "cadence_tier": "medium",
      "language_hint": "en",
      "enabled": true,
      "top50_relevance_mode": "symbol_alias_match",
      "applies_to_assets": "all_major_50"
    },
    {
      "source_id": "derivatives_binance_usdm_funding_rate_history_rest",
      "source_category": "funding",
      "source_name": "Binance USD-M Futures Funding Rate History",
      "source_url": "https://fapi.binance.com/fapi/v1/fundingRate",
      "fetch_method": "rest_api",
      "adapter": "binance_usdm_funding_rate_history",
      "max_items_per_run": 1000,
      "trust_tier": "T1",
      "cadence_tier": "medium",
      "language_hint": "en",
      "enabled": false,
      "source_state": "available_disabled",
      "activation_blocker": "manual_backfill_requires_start_end_ms",
      "top50_relevance_mode": "symbol_alias_match",
      "applies_to_assets": "all_major_50"
    },
    {
      "source_id": "derivatives_binance_usdm_open_interest_rest",
      "source_category": "funding",
      "source_name": "Binance USD-M Futures Open Interest",
      "source_url": "https://fapi.binance.com/fapi/v1/openInterest",
      "fetch_method": "rest_api",
      "adapter": "binance_usdm_open_interest",
      "max_items_per_run": 50,
      "trust_tier": "T1",
      "cadence_tier": "medium",
      "language_hint": "en",
      "enabled": true,
      "top50_relevance_mode": "symbol_alias_match",
      "applies_to_assets": "all_major_50"
    },
    {
      "source_id": "governance_uniswap_rss",
      "source_category": "governance",
      "source_name": "Uniswap Governance RSS",
      "source_url": "https://gov.uniswap.org/latest.rss",
      "fetch_method": "rss",
      "trust_tier": "T1",
      "cadence_tier": "low",
      "language_hint": "en",
      "enabled": true,
      "top50_relevance_mode": "direct_asset",
      "applies_to_assets": ["UNI"]
    },
    {
      "source_id": "governance_aave_rss",
      "source_category": "governance",
      "source_name": "Aave Governance RSS",
      "source_url": "https://governance.aave.com/latest.rss",
      "fetch_method": "rss",
      "trust_tier": "T1",
      "cadence_tier": "low",
      "language_hint": "en",
      "enabled": true,
      "top50_relevance_mode": "direct_asset",
      "applies_to_assets": ["AAVE"]
    },
    {
      "source_id": "governance_avalanche_forum_rss",
      "source_category": "governance",
      "source_name": "Avalanche Forum RSS",
      "source_url": "https://forum.avax.network/latest.rss",
      "fetch_method": "rss",
      "trust_tier": "T1",
      "cadence_tier": "low",
      "language_hint": "en",
      "enabled": true,
      "top50_relevance_mode": "direct_asset",
      "applies_to_assets": ["AVAX"]
    },
    {
      "source_id": "dev_btc_github_releases_atom",
      "source_category": "developer_activity",
      "source_name": "Bitcoin Core GitHub Releases Atom",
      "source_url": "https://github.com/bitcoin/bitcoin/releases.atom",
      "fetch_method": "rss",
      "trust_tier": "T0",
      "cadence_tier": "low",
      "language_hint": "en",
      "enabled": true,
      "top50_relevance_mode": "direct_asset",
      "applies_to_assets": ["BTC"]
    },
    {
      "source_id": "dev_eth_geth_github_releases_atom",
      "source_category": "developer_activity",
      "source_name": "Go Ethereum GitHub Releases Atom",
      "source_url": "https://github.com/ethereum/go-ethereum/releases.atom",
      "fetch_method": "rss",
      "trust_tier": "T0",
      "cadence_tier": "low",
      "language_hint": "en",
      "enabled": true,
      "top50_relevance_mode": "direct_asset",
      "applies_to_assets": ["ETH"]
    },
    {
      "source_id": "dev_sol_github_releases_atom",
      "source_category": "developer_activity",
      "source_name": "Solana GitHub Releases Atom",
      "source_url": "https://github.com/solana-labs/solana/releases.atom",
      "fetch_method": "rss",
      "trust_tier": "T1",
      "cadence_tier": "low",
      "language_hint": "en",
      "enabled": true,
      "top50_relevance_mode": "direct_asset",
      "applies_to_assets": ["SOL"]
    },
    {
      "source_id": "dev_sui_github_releases_atom",
      "source_category": "developer_activity",
      "source_name": "Sui GitHub Releases Atom",
      "source_url": "https://github.com/MystenLabs/sui/releases.atom",
      "fetch_method": "rss",
      "trust_tier": "T1",
      "cadence_tier": "low",
      "language_hint": "en",
      "enabled": true,
      "top50_relevance_mode": "direct_asset",
      "applies_to_assets": ["SUI"]
    },
    {
      "source_id": "dev_link_github_releases_atom",
      "source_category": "developer_activity",
      "source_name": "Chainlink GitHub Releases Atom",
      "source_url": "https://github.com/smartcontractkit/chainlink/releases.atom",
      "fetch_method": "rss",
      "trust_tier": "T1",
      "cadence_tier": "low",
      "language_hint": "en",
      "enabled": true,
      "top50_relevance_mode": "direct_asset",
      "applies_to_assets": ["LINK"]
    },
    {
      "source_id": "dev_avax_github_releases_atom",
      "source_category": "developer_activity",
      "source_name": "AvalancheGo GitHub Releases Atom",
      "source_url": "https://github.com/ava-labs/avalanchego/releases.atom",
      "fetch_method": "rss",
      "trust_tier": "T1",
      "cadence_tier": "low",
      "language_hint": "en",
      "enabled": true,
      "top50_relevance_mode": "direct_asset",
      "applies_to_assets": ["AVAX"]
    },
    {
      "source_id": "dev_aave_github_releases_atom",
      "source_category": "developer_activity",
      "source_name": "Aave V3 Core GitHub Releases Atom",
      "source_url": "https://github.com/aave/aave-v3-core/releases.atom",
      "fetch_method": "rss",
      "trust_tier": "T1",
      "cadence_tier": "low",
      "language_hint": "en",
      "enabled": true,
      "top50_relevance_mode": "direct_asset",
      "applies_to_assets": ["AAVE"]
    },
    {
      "source_id": "dev_uni_github_releases_atom",
      "source_category": "developer_activity",
      "source_name": "Uniswap V4 Core GitHub Releases Atom",
      "source_url": "https://github.com/Uniswap/v4-core/releases.atom",
      "fetch_method": "rss",
      "trust_tier": "T1",
      "cadence_tier": "low",
      "language_hint": "en",
      "enabled": true,
      "top50_relevance_mode": "direct_asset",
      "applies_to_assets": ["UNI"]
    },
    {
      "source_id": "dev_ton_github_releases_atom",
      "source_category": "developer_activity",
      "source_name": "TON GitHub Releases Atom",
      "source_url": "https://github.com/ton-blockchain/ton/releases.atom",
      "fetch_method": "rss",
      "trust_tier": "T1",
      "cadence_tier": "low",
      "language_hint": "en",
      "enabled": true,
      "top50_relevance_mode": "direct_asset",
      "applies_to_assets": ["TON"]
    },
    {
      "source_id": "dev_zec_github_releases_atom",
      "source_category": "developer_activity",
      "source_name": "Zcash GitHub Releases Atom",
      "source_url": "https://github.com/zcash/zcash/releases.atom",
      "fetch_method": "rss",
      "trust_tier": "T1",
      "cadence_tier": "low",
      "language_hint": "en",
      "enabled": true,
      "top50_relevance_mode": "direct_asset",
      "applies_to_assets": ["ZEC"]
    },
    {
      "source_id": "dev_doge_github_releases_atom",
      "source_category": "developer_activity",
      "source_name": "Dogecoin GitHub Releases Atom",
      "source_url": "https://github.com/dogecoin/dogecoin/releases.atom",
      "fetch_method": "rss",
      "trust_tier": "T1",
      "cadence_tier": "low",
      "language_hint": "en",
      "enabled": true,
      "top50_relevance_mode": "direct_asset",
      "applies_to_assets": ["DOGE"]
    },
    {
      "source_id": "dev_trx_github_releases_atom",
      "source_category": "developer_activity",
      "source_name": "java-tron GitHub Releases Atom",
      "source_url": "https://github.com/tronprotocol/java-tron/releases.atom",
      "fetch_method": "rss",
      "trust_tier": "T1",
      "cadence_tier": "low",
      "language_hint": "en",
      "enabled": true,
      "top50_relevance_mode": "direct_asset",
      "applies_to_assets": ["TRX"]
    },
    {
      "source_id": "dev_near_github_releases_atom",
      "source_category": "developer_activity",
      "source_name": "NEAR Core GitHub Releases Atom",
      "source_url": "https://github.com/near/nearcore/releases.atom",
      "fetch_method": "rss",
      "trust_tier": "T1",
      "cadence_tier": "low",
      "language_hint": "en",
      "enabled": true,
      "top50_relevance_mode": "direct_asset",
      "applies_to_assets": ["NEAR"]
    },
    {
      "source_id": "dev_ada_github_releases_atom",
      "source_category": "developer_activity",
      "source_name": "Cardano Node GitHub Releases Atom",
      "source_url": "https://github.com/IntersectMBO/cardano-node/releases.atom",
      "fetch_method": "rss",
      "trust_tier": "T1",
      "cadence_tier": "low",
      "language_hint": "en",
      "enabled": true,
      "top50_relevance_mode": "direct_asset",
      "applies_to_assets": ["ADA"]
    },
    {
      "source_id": "dev_ltc_github_releases_atom",
      "source_category": "developer_activity",
      "source_name": "Litecoin Core GitHub Releases Atom",
      "source_url": "https://github.com/litecoin-project/litecoin/releases.atom",
      "fetch_method": "rss",
      "trust_tier": "T1",
      "cadence_tier": "low",
      "language_hint": "en",
      "enabled": true,
      "top50_relevance_mode": "direct_asset",
      "applies_to_assets": ["LTC"]
    },
    {
      "source_id": "dev_bch_github_releases_atom",
      "source_category": "developer_activity",
      "source_name": "Bitcoin Cash Node GitHub Releases Atom",
      "source_url": "https://github.com/bitcoin-cash-node/bitcoin-cash-node/releases.atom",
      "fetch_method": "rss",
      "trust_tier": "T1",
      "cadence_tier": "low",
      "language_hint": "en",
      "enabled": true,
      "top50_relevance_mode": "direct_asset",
      "applies_to_assets": ["BCH"]
    },
    {
      "source_id": "social_hackernews_crypto_rss",
      "source_category": "social",
      "source_name": "Hacker News Crypto Search RSS",
      "source_url": "https://hnrss.org/newest?q=crypto",
      "fetch_method": "rss",
      "max_items_per_run": 5,
      "trust_tier": "T2",
      "cadence_tier": "medium",
      "language_hint": "en",
      "enabled": false,
      "source_state": "available_disabled",
      "activation_blocker": "unstable_external_source_http_502",
      "top50_relevance_mode": "symbol_alias_match",
      "applies_to_assets": "all_major_50"
    },
    {
      "source_id": "social_hackernews_bitcoin_rss",
      "source_category": "social",
      "source_name": "Hacker News Bitcoin Search RSS",
      "source_url": "https://hnrss.org/newest?q=bitcoin",
      "fetch_method": "rss",
      "max_items_per_run": 5,
      "trust_tier": "T2",
      "cadence_tier": "medium",
      "language_hint": "en",
      "enabled": false,
      "source_state": "available_disabled",
      "activation_blocker": "unstable_external_source_http_502",
      "top50_relevance_mode": "direct_asset",
      "applies_to_assets": ["BTC"]
    },
    {
      "source_id": "social_hackernews_ethereum_rss",
      "source_category": "social",
      "source_name": "Hacker News Ethereum Search RSS",
      "source_url": "https://hnrss.org/newest?q=ethereum",
      "fetch_method": "rss",
      "max_items_per_run": 5,
      "trust_tier": "T2",
      "cadence_tier": "medium",
      "language_hint": "en",
      "enabled": false,
      "source_state": "available_disabled",
      "activation_blocker": "unstable_external_source_http_502",
      "top50_relevance_mode": "direct_asset",
      "applies_to_assets": ["ETH"]
    },
    {
      "source_id": "social_hackernews_solana_rss",
      "source_category": "social",
      "source_name": "Hacker News Solana Search RSS",
      "source_url": "https://hnrss.org/newest?q=solana",
      "fetch_method": "rss",
      "max_items_per_run": 5,
      "trust_tier": "T2",
      "cadence_tier": "medium",
      "language_hint": "en",
      "enabled": false,
      "source_state": "available_disabled",
      "activation_blocker": "unstable_external_source_http_502",
      "top50_relevance_mode": "direct_asset",
      "applies_to_assets": ["SOL"]
    },
    {
      "source_id": "social_reddit_cryptocurrency_new_rss",
      "source_category": "social",
      "source_name": "Reddit r/CryptoCurrency New RSS",
      "source_url": "https://www.reddit.com/r/CryptoCurrency/new/.rss",
      "fetch_method": "rss",
      "trust_tier": "T2",
      "cadence_tier": "high",
      "language_hint": "en",
      "enabled": false,
      "source_state": "available_disabled",
      "activation_blocker": "reqwest_http_403_default_disabled",
      "top50_relevance_mode": "symbol_alias_match",
      "applies_to_assets": "all_major_50"
    },
    {
      "source_id": "social_reddit_cryptomarkets_new_rss",
      "source_category": "social",
      "source_name": "Reddit r/CryptoMarkets New RSS",
      "source_url": "https://www.reddit.com/r/CryptoMarkets/new/.rss",
      "fetch_method": "rss",
      "trust_tier": "T2",
      "cadence_tier": "high",
      "language_hint": "en",
      "enabled": false,
      "source_state": "available_disabled",
      "activation_blocker": "reqwest_http_403_default_disabled",
      "top50_relevance_mode": "symbol_alias_match",
      "applies_to_assets": "all_major_50"
    },
    {
      "source_id": "social_reddit_bitcoin_new_rss",
      "source_category": "social",
      "source_name": "Reddit r/Bitcoin New RSS",
      "source_url": "https://www.reddit.com/r/Bitcoin/new/.rss",
      "fetch_method": "rss",
      "trust_tier": "T2",
      "cadence_tier": "high",
      "language_hint": "en",
      "enabled": false,
      "source_state": "available_disabled",
      "activation_blocker": "reqwest_http_403_default_disabled",
      "top50_relevance_mode": "direct_asset",
      "applies_to_assets": ["BTC"]
    },
    {
      "source_id": "social_reddit_ethereum_new_rss",
      "source_category": "social",
      "source_name": "Reddit r/ethereum New RSS",
      "source_url": "https://www.reddit.com/r/ethereum/new/.rss",
      "fetch_method": "rss",
      "trust_tier": "T2",
      "cadence_tier": "high",
      "language_hint": "en",
      "enabled": false,
      "source_state": "available_disabled",
      "activation_blocker": "reqwest_http_403_default_disabled",
      "top50_relevance_mode": "direct_asset",
      "applies_to_assets": ["ETH"]
    },
    {
      "source_id": "social_reddit_ethfinance_new_rss",
      "source_category": "social",
      "source_name": "Reddit r/ethfinance New RSS",
      "source_url": "https://www.reddit.com/r/ethfinance/new/.rss",
      "fetch_method": "rss",
      "trust_tier": "T2",
      "cadence_tier": "high",
      "language_hint": "en",
      "enabled": false,
      "source_state": "available_disabled",
      "activation_blocker": "reqwest_http_403_default_disabled",
      "top50_relevance_mode": "direct_asset",
      "applies_to_assets": ["ETH"]
    },
    {
      "source_id": "social_reddit_solana_new_rss",
      "source_category": "social",
      "source_name": "Reddit r/solana New RSS",
      "source_url": "https://www.reddit.com/r/solana/new/.rss",
      "fetch_method": "rss",
      "trust_tier": "T2",
      "cadence_tier": "high",
      "language_hint": "en",
      "enabled": false,
      "source_state": "available_disabled",
      "activation_blocker": "reqwest_http_403_default_disabled",
      "top50_relevance_mode": "direct_asset",
      "applies_to_assets": ["SOL"]
    },
    {
      "source_id": "social_reddit_chainlink_new_rss",
      "source_category": "social",
      "source_name": "Reddit r/Chainlink New RSS",
      "source_url": "https://www.reddit.com/r/Chainlink/new/.rss",
      "fetch_method": "rss",
      "trust_tier": "T2",
      "cadence_tier": "high",
      "language_hint": "en",
      "enabled": false,
      "source_state": "available_disabled",
      "activation_blocker": "reqwest_http_403_default_disabled",
      "top50_relevance_mode": "direct_asset",
      "applies_to_assets": ["LINK"]
    },
    {
      "source_id": "social_reddit_sui_new_rss",
      "source_category": "social",
      "source_name": "Reddit r/sui New RSS",
      "source_url": "https://www.reddit.com/r/sui/new/.rss",
      "fetch_method": "rss",
      "trust_tier": "T2",
      "cadence_tier": "high",
      "language_hint": "en",
      "enabled": false,
      "source_state": "available_disabled",
      "activation_blocker": "reqwest_http_403_default_disabled",
      "top50_relevance_mode": "direct_asset",
      "applies_to_assets": ["SUI"]
    },
    {
      "source_id": "project_btc_bitcoin_core_rss",
      "source_category": "project_notice",
      "source_name": "Bitcoin Core RSS",
      "source_url": "https://bitcoincore.org/en/rss.xml",
      "fetch_method": "rss",
      "trust_tier": "T0",
      "cadence_tier": "low",
      "language_hint": "en",
      "enabled": true,
      "top50_relevance_mode": "direct_asset",
      "applies_to_assets": ["BTC"]
    },
    {
      "source_id": "project_btc_bitcoin_optech_rss",
      "source_category": "project_notice",
      "source_name": "Bitcoin Optech RSS",
      "source_url": "https://bitcoinops.org/feed.xml",
      "fetch_method": "rss",
      "trust_tier": "T1",
      "cadence_tier": "low",
      "language_hint": "en",
      "enabled": true,
      "top50_relevance_mode": "direct_asset",
      "applies_to_assets": ["BTC"]
    },
    {
      "source_id": "project_eth_ethereum_blog_rss",
      "source_category": "project_notice",
      "source_name": "Ethereum Foundation Blog RSS",
      "source_url": "https://blog.ethereum.org/feed.xml",
      "fetch_method": "rss",
      "trust_tier": "T0",
      "cadence_tier": "low",
      "language_hint": "en",
      "enabled": true,
      "top50_relevance_mode": "direct_asset",
      "applies_to_assets": ["ETH"]
    },
    {
      "source_id": "project_sol_solana_news_rss",
      "source_category": "project_notice",
      "source_name": "Solana News RSS",
      "source_url": "https://solana.com/news/rss.xml",
      "fetch_method": "rss",
      "trust_tier": "T0",
      "cadence_tier": "low",
      "language_hint": "en",
      "enabled": true,
      "top50_relevance_mode": "direct_asset",
      "applies_to_assets": ["SOL"]
    },
    {
      "source_id": "project_sui_blog_rss",
      "source_category": "project_notice",
      "source_name": "Sui Blog RSS",
      "source_url": "https://blog.sui.io/rss/",
      "fetch_method": "rss",
      "trust_tier": "T0",
      "cadence_tier": "low",
      "language_hint": "en",
      "enabled": true,
      "top50_relevance_mode": "direct_asset",
      "applies_to_assets": ["SUI"]
    },
    {
      "source_id": "project_link_chainlink_blog_rss",
      "source_category": "project_notice",
      "source_name": "Chainlink Blog RSS",
      "source_url": "https://blog.chain.link/feed/",
      "fetch_method": "rss",
      "trust_tier": "T0",
      "cadence_tier": "low",
      "language_hint": "en",
      "enabled": true,
      "top50_relevance_mode": "direct_asset",
      "applies_to_assets": ["LINK"]
    },
    {
      "source_id": "project_glm_golem_blog_rss",
      "source_category": "project_notice",
      "source_name": "Golem Blog RSS",
      "source_url": "https://blog.golem.network/feed/",
      "fetch_method": "rss",
      "trust_tier": "T0",
      "cadence_tier": "low",
      "language_hint": "en",
      "enabled": false,
      "source_state": "available_disabled",
      "activation_blocker": "outside_current_major_50_universe",
      "top50_relevance_mode": "direct_asset",
      "applies_to_assets": ["GLM"]
    },
    {
      "source_id": "project_zil_zilliqa_blog_rss",
      "source_category": "project_notice",
      "source_name": "Zilliqa Blog RSS",
      "source_url": "https://blog.zilliqa.com/feed",
      "fetch_method": "rss",
      "trust_tier": "T0",
      "cadence_tier": "low",
      "language_hint": "en",
      "enabled": false,
      "source_state": "available_disabled",
      "activation_blocker": "outside_current_major_50_universe",
      "top50_relevance_mode": "direct_asset",
      "applies_to_assets": ["ZIL"]
    },
    {
      "source_id": "project_axl_axelar_blog_rss",
      "source_category": "project_notice",
      "source_name": "Axelar Blog RSS",
      "source_url": "https://www.axelar.network/blog/rss.xml",
      "fetch_method": "rss",
      "trust_tier": "T0",
      "cadence_tier": "low",
      "language_hint": "en",
      "enabled": false,
      "source_state": "available_disabled",
      "activation_blocker": "outside_current_major_50_universe",
      "top50_relevance_mode": "direct_asset",
      "applies_to_assets": ["AXL"]
    }
  ],
  "probe_backlog": [
    { "asset": "ADA", "candidate_url": "https://cardanofoundation.org/blog/rss.xml", "result": "not_enabled", "reason": "returned challenge or rate-limit page during probe" },
    { "asset": "ADA", "candidate_url": "https://iohk.io/en/blog/posts/page-1/index.xml", "result": "not_enabled", "reason": "returned Cloudflare challenge during probe" },
    { "asset": "AVAX", "candidate_url": "https://www.avax.network/blog/rss.xml", "result": "not_enabled", "reason": "redirected path did not verify as RSS" },
    { "asset": "DOGE", "candidate_url": "https://foundation.dogecoin.com/feed.xml", "result": "not_enabled", "reason": "returned 404 during probe" },
    { "asset": "ETC", "candidate_url": "https://ethereumclassic.org/blog/rss.xml", "result": "not_enabled", "reason": "returned 404 during probe" },
    { "asset": "FIL", "candidate_url": "https://filecoin.io/blog/feed/index.xml", "result": "not_enabled", "reason": "returned 404 during probe" },
    { "asset": "NEAR", "candidate_url": "https://near.org/blog/rss.xml", "result": "not_enabled", "reason": "returned HTML instead of RSS during probe" },
    { "asset": "XLM", "candidate_url": "https://stellar.org/blog/feed.xml", "result": "not_enabled", "reason": "returned 404 during probe" },
    { "asset": "XRP", "candidate_url": "https://ripple.com/insights/feed/", "result": "not_enabled", "reason": "returned 404 during probe" }
  ]
}
